{
  "push_child_transferred_to_savings": "{transaction.child.name} har opsparet {transaction.str_value}",
  "push_goal_created": "{goal.created_by.name} har oprettet opsparingsmålet {goal.title}",
  "push_goal_completed_child": "Du har opnået opsparingsmålet {goal.title}",
  "push_goal_completed_parent": "{goal.child.name} har opnået opsparingsmålet {goal.title}",
  "push_withdrawal_child": "{transaction.created_by.name} trak {transaction.str_value} fra sparegrisen",
  "push_withdrawal_parent": "{transaction.created_by.name} hævet {transaction.str_value} fra {transaction.child.name} s sparegris",
  "push_timed_assignment_expired": "Du nåede det desværre ikke {assignment.task.title}",
  "push_connected_with_parent": "Tjuhej! Du er nu blevet koblet sammen med en forælder",
  "push_invite_accepted": "{user} har lige accepteret din indbydelse",
  "push_assignment_created": "Yihaa! Du har fået en ny opgave",
  "push_assignment_active_again": "Opgaven {assignment.task.title} er tilgængelig igen. Først til mølle",
  "push_assignment_done": "{assignment.child.name} har lige udført {assignment.task.title}",
  "push_assignment_done_by_other": "Du var ikke hurtig nok! {child.name} udførte {assignment.task.title} inden dig",
  "push_assignment_rejected": "Opgaven {assignment.task.title} blev desværre ikke godkendt. Prøv igen",
  "push_assignment_approved": "Tillykke! {assignment.approved_by.name} har lige godkendt {assignment.task.title} ({assignment.str_value})",
  "push_insertion_by_other": "Nice! {transaction.created_by.name} har lige sat {transaction.str_value} ind på din sparegris",
  "push_account_select_started": "Registrering af bankkonto er i gang",
  "push_parent_account_selected": "Din bankkonto er aktiveret",
  "push_child_account_selected": "{child.name}s bankkonto er aktiveret",
  "push_weekly_trustly_payout_failed_parent": "Overførelse af {transaction.parent.name}s ugentlige lommepenge mislykkedes",
  "push_monthly_trustly_payout_failed_parent": "Overførelse af {transaction.parent.name}s månedlige lommepenge mislykkedes",
  "push_weekly_trustly_payout_trustly_failed_child": "Overførelse af dine ugentlige lommepenge mislykkedes",
  "push_monthly_trustly_payout_trustly_failed_child": "Overførelse af dine månedlige lommepenge mislykkedes",
  "push_changed_to_weekly_allowance": "{name} er gået over til ugepenge",
  "push_changed_to_monthly_allowance": "{name} er gået over til månedspenge",
  "push_trustly_weekly_allowance_parent_changed": "Nu betales {child}s ugentlige lommepenge fra din konto",
  "push_trustly_monthly_allowance_parent_changed": "Nu betales {child}s månedlige lommepenge fra din konto",
  "push_trustly_weekly_allowance_parent_changed_2": "Nu udbetales {child} s ugentlig ydelse fra {parent}  s konto",
  "push_trustly_monthly_allowance_parent_changed_2": "Nu udbetales {child} s månedlige ydelse fra {parent}  s konto",
  "push_trustly_weekly_allowance_parent_changed_child": "Nu er din ugentlig ydelse udbetalt til din bankkonto hver uge",
  "push_trustly_monthly_allowance_parent_changed_child": "Nu er din månedlig ydelse udbetalt til din bankkonto hvert måned",
  "dashboard_interest_added": "Fik {transaction.str_value} i opsparingsbonus",
  "dashboard_changed_to_weekly_allowance": "Er gået over til ugentlige lommepenge",
  "dashboard_changed_to_monthly_allowance": "Er gået over til månedlige lommepenge",
  "trustly_charge_over_limit_email_subject": "Vigtig meddelelse om udbetaling",
  "trustly_charge_failed_email_subject": "Meddelelse om mislykket udbetaling",
  "trustly_payout_failed_email_subject": "Meddelelse om mislykket udbetaling og tilbagebetaling",
  "invite_email_subject": "Inviter til Gimi",
  "login_email_subject": "Log ind på Gimi",
  "push_trustly_over_limit": "Mislykket overførsel på {amount}",
  "dashboard_goal_created": "Oprettede opsparingsmål {goal.title}",
  "dashboard_goal_completed": "Opsparingsmålet er opnået {goal.title}",
  "dashboard_transfer_to_savings": "Opsparet {transaction.str_value}",
  "push_task_updated": "{user} har ændret opgaven {task}",
  "dashboard_child_not_connected": "Glem ikke at tilslutte dig",
  "dashboard_child_setup": "Er ikke færdigoprettet endnu",
  "dashboard_weekly_allowance_over_trustly_limit": "Ugentlig lommepenge er over beløbsgrænsen",
  "dashboard_monthly_allowance_over_trustly_limit": "Månedlig lommepenge er over beløbsgrænsen",
  "dashboard_failed_trustly_transaction": "Mislykket overførsel",
  "dashboard_completed_trustly_transaction": "{transaction.str_value} overførtes til bankkonto",
  "dashboard_assignment_completed": "Klar med {assignment.task.title}",
  "dashboard_child_trustly_account_ongoing": "Afventer tilslutning til bankkontoen",
  "dashboard_goal_archived": "Arkiverede sparemålet {goal.title}",
  "dashboard_child_trustly_allowance_enabled": "Overførsler aktiverede",
  "dashboard_add_trustly_account": "Tilføj Bankkonto",
  "push_first_wish_created": "{wish.child.name} har oprettet ønskeseddel og har anmodet om en {wish.title}",
  "push_wish_created": "{wish.child.name} har tilføjet {wish.title} til ønskelisten",
  "push_wish_deleted": "{wish.child.name} har slettet {wish.title} fra ønskelisten",
  "push_child_logged_in": "{child.name} er logget på",
  "sms_app_download": "Velkommen til Ugepenge!\n http//onelink.to/t69wn8",
  "push_goal_archived": "{goal.updated_by.name} gemte opsparingsmålet {goal.title}",
  "push_timed_assignment_created": "Gå ind og kig, du har fået en tidsbegrænset opgave",
  "push_shared_assignment_created": "Kig ind i appen, du konkurrerer om at fuldføre en opgave",
  "push_repeating_assignment_created": "Kig ind! Du har en ny opgave, som kan gentages",
  "push_check_wish_list": "Et måned tilbage til din fødselsdag. Tjek ønskelisten",
  "push_assignment_approved_parent": "{assignment.approved_by.name} godkendte opgaven {assignment.task.title}. ({assignment.str_value})",
  "dashboard_assignment_approved": "Opgaven {assignment.task.title} blev godkendt. ({assignment.str_value})",
  "push_task_enabled": "Nu kan du udføre opgaven {task}",
  "push_disabled_task_created": "{child} har foreslået opgave {task}",
  "push_weekly_payout_message_parent": "{transaction.str_value} af ugentlig ydelse blev overført til {transaction.child.name} s bankkonto",
  "push_monthly_payout_message_parent": "{transaction.str_value} af det månedlig ydelse blev overført til {transaction.child.name} s bankkonto",
  "push_charge_message_parent": "I øjeblikket overføres {amount} til {child} bankkonto i morgen",
  "dashboard_disabled_task_created": "Foreslået opgave {task}",
  "push_trustly_mandate_revoked": "Din bankkonto er nu deaktiveret, opdater dine oplysninger for at bruge bankoverførsler",
  "push_weekly_allowance_pre_payout_parent_0": "Tid til {child}s ugentlig lommepenge",
  "push_weekly_allowance_pre_payout_parent_1": "Tid til {child}s ugentlig lommepenge",
  "push_weekly_allowance_pre_payout_parent_2": "Tid til {child}s ugentlig lommepenge",
  "push_weekly_allowance_pre_payout_parent_3": "Tid til {child}s ugentlig lommepenge",
  "push_weekly_allowance_pre_payout_parent_4": "Tid til {child}s ugentlig lommepenge",
  "push_monthly_allowance_pre_payout_parent_0": "Tid til {child}s månedlig lommepenge",
  "push_monthly_allowance_pre_payout_parent_1": "Tid til {child}s månedlig lommepenge",
  "push_monthly_allowance_pre_payout_parent_2": "Tid til {child}s månedlig lommepenge",
  "push_monthly_allowance_pre_payout_parent_3": "Tid til {child}s månedlig lommepenge",
  "push_monthly_allowance_pre_payout_parent_4": "Tid til {child}s månedlig lommepenge",
  "push_weekly_assignment_0": "I dag, kan du {task} for {value}, hvilket deal",
  "push_weekly_assignment_1": "Godmorgen venner! I dag kan du tjene {value}! Gå ind i appen og se hvilken opgave du kan udføre",
  "push_weekly_assignment_2": "Du har modtaget en ny opgave: {task} Gå ind i appen og tjek hvad du kan tjene",
  "push_weekly_assignment_3": "Ny opgave! Yay! Du kan blive {value} rigere! Gå ind i appen og tjek hvilke opgaver du kan udføre",
  "push_weekly_assignment_4": "Ny opgave! {task} Box! Gå ind i appen og se, hvad du kan tjene",
  "push_weekly_allowance_trustly_pre_payout": "Udbetaling i morgen.  Lige nu er der {amount} i ugentlig ydelse til {child}s bankkonto",
  "push_monthly_allowance_trustly_pre_payout": "Udbetaling i morgen. Lige nu er der {amount} i månedlig ydelse til {child}s bankkonto",
  "push_weekly_interest_added_0": "Tillykke! Ugens opsparingsbonus er lagt i sparegrisen",
  "push_weekly_interest_added_1": "Tillykke! Ugens opsparingsbonus er lagt i sparegrisen",
  "push_weekly_interest_added_2": "Tillykke! Ugens opsparingsbonus er lagt i sparegrisen",
  "push_weekly_interest_added_3": "Tillykke! Ugens opsparingsbonus er lagt i sparegrisen",
  "push_weekly_interest_added_4": "Tillykke! Ugens opsparingsbonus er lagt i sparegrisen",
  "push_monthly_interest_added_0": "Tillykke! Månedens opsparingsbonus er lagt i sparegrisen",
  "push_monthly_interest_added_1": "Tillykke! Månedens opsparingsbonus er lagt i sparegrisen",
  "push_monthly_interest_added_2": "Tillykke! Månedens opsparingsbonus er lagt i sparegrisen",
  "push_monthly_interest_added_3": "Tillykke! Månedens opsparingsbonus er lagt i sparegrisen",
  "push_monthly_interest_added_4": "Tillykke! Månedens opsparingsbonus er lagt i sparegrisen",
  "push_new_weekly_tasks_0": "Kig! Du har fået nye opgaver",
  "push_new_weekly_tasks_1": "Kig! Du har fået nye opgaver",
  "push_new_weekly_tasks_2": "Kig! Du har fået nye opgaver",
  "push_new_weekly_tasks_3": "Kig! Du har fået nye opgaver",
  "push_new_weekly_tasks_4": "Kig! Du har fået nye opgaver",
  "push_goal_activated": "{goal.updated_by.name} har oprettet et opsparingsmål {goal.title}",
  "push_goal_sponsored": "{goal.updated_by.name} sponsoreret opsparingsmålet {goal.title}",
  "push_goal_boost_decreased": "Du har mistet et boost på dit opsparingsmål",
  "push_goal_boosts_decreased": "Du har tabt boosts på dit opsparingsmål",
  "dashboard_goal_boost_decreased": "Mistet et boost på opsparingsmålskortet",
  "dashboard_goal_boosts_decreased": "Mistet øgelse på opsparingsmålskortet",
  "push_goal_almost_completed": "Godt arbejde! Du er næsten færdig med dit opsparingsmål",
  "push_duration_assignment_created": "Du har fået en ny opgave",
  "event_task_created": "{task.owner.name} oprettet opgave: {task.title}",
  "event_task_updated": "{user.nickname} opdateret opgave: {task.title}",
  "event_task_suggested": "{task.owner.name} foreslået opgave: {task.title}",
  "event_task_deleted": "{user.nickname} fjernet opgave: {task.title}",
  "event_assignment_rejected": "{user.nickname} afvist opgave: {assignment.task.title}",
  "event_assignment_approved": "{assignment.approved_by.name} godkendt opgave: {assignment.task.title}",
  "event_assignment_expired": "{assignment.child.name} lykkedes ikke at fuldføre opgaven: {assignment.task.title} i tide",
  "event_assignment_completed_by_other": "{assignment.task.shared_task_completed_by} gennemført opgaven {assignment.task.title} først",
  "event_goal_created": "{goal.created_by.name} oprettet opsparingsmål {goal.title}",
  "event_goal_updated": "{goal.updated_by.name} opdateret opsparingsmål {goal.title}",
  "event_goal_deleted": "{user.nickname} fjernet opsparingsmål {goal.title}",
  "event_goal_completed": "{goal.child.name} gennemført opsparingsmål {goal.title}",
  "event_wish_created": "{wish.child.name} tilføjede et nyt ønske: {wish.title}",
  "event_wish_updated": "{wish.updated_by.name} opdateret ønske: {wish.title}",
  "event_wish_deleted": "{user.nickname} fjernet ønske: {wish.title}",
  "event_birthday": "{child.name} fødselsdag i dag",
  "event_assignment_reminder": "{parent.name} lige sendt dig en påmindelse til {assignment.task.title}",
  "push_assignment_reminder": "{parent.name} lige sendt dig en påmindelse til {assignment.task.title}",
  "push_new_app_version": "En ny opdatering kommer i appbutikken",
  "push_manual_trustly_withdrawal": "{transaction.str_value} er overført til {transaction.child.name} s bankkonto",
  "push_manual_trustly_withdrawal_failed_parent": "Overførslen af {transaction.str_value} til {transaction.child.name} s bankkonto ugentlige ydelse var mislykket",
  "push_manual_trustly_withdrawal_failed_child": "Overførsel af {transaction.str_value} til din bankkonto mislykkedes",
  "push_event_message_created": "{user.nickname}: \"{text}\"",
  "push_assignment_auto_approved": "Flot! {assignment.task.title} blev automatisk godkendt",
  "push_assignment_auto_approved_parent": "Opgave er automatisk godkendt: {assignment.task.title}",
  "event_assignment_auto_approved": "Opgaven er automatisk godkendt: {assignment.task.title}",
  "dashboard_connected_parent": "Du er nu forbundet med {child.name}",
  "push_before_super_parent": "Du er nu tæt på at blive en superforælder! Det eneste der er tilbage at gøre, er at forbinde dig med dit barn",
  "push_intro_chores": "Fedt at se dig sammen med os! Nu er det tid til at uddele nogle opgaver til dine børn. Er du villig til at betale 5 kr. for at undgå aftenopvasken? :-)",
  "push_intro_make_deposit": "Det er tid til at gøre dine børns kontanter digitale. Lav et depositum i spargrisen for at få dine børn til at vokse financielt",
  "push_reminder_give_chores": "Glem ikke at give dine børn opgaver så de kan tjene nogle ekstra penge, samtidig med at de lærer hvordan pengene fungerer. Find eksempelopgaver i appen",
  "push_suggest_task": "Du kan nu foreslå opgaver til dine forældre. Vælg Opgaver i appen og giv derefter et forslag til en opgave. På denne måde kan du tjene nogle ekstra penge",
  "push_exchange_cash": "Har du kontanter? Udveksel dine penge med dine forældre og bed dem om et depositum i din sparegris",
  "push_weekly_allowance_pre_payout_0": "I dag fik {child} hans ugentlige sats i sin spargris!",
  "push_weekly_allowance_pre_payout_1": "{child} har fået sin ugentlig ydelse i dag!",
  "push_weekly_allowance_pre_payout_2": "{child} s lommepenge er blevet overført til sparegrisen, klirr!",
  "push_weekly_allowance_pre_payout_3": "Betalingsdag! {child} har fået den ugentlig ydelse overført til sin sparegris!",
  "push_weekly_allowance_pre_payout_4": "Lommepengedag! {child} s ugentlig ydelse er blevet overført til sparegrisen!",
  "push_monthly_allowance_pre_payout_0": "I dag har {child} fået sin månedlige lommepenge overført til sin sparegris!",
  "push_monthly_allowance_pre_payout_1": "{child} har modtaget sine månedlige lommepenge i dag!",
  "push_monthly_allowance_pre_payout_2": "{child} s månedlige lommepenge er blevet overført til sin spargrisen, klirr!",
  "push_monthly_allowance_pre_payout_3": "Udtalingsdag! {child} har fået månedens bonus overført til sin sparegris!",
  "push_monthly_allowance_pre_payout_4": "Månedlig lommepengedag! {child} s månedlig lommepenge er blevet overført til sin spargrisen!",
  "push_remind_parent_child_weekly_money": "Vidste du, at hvis du er tilsluttet med dine forældre, vil de hver uge blive mindet om, om de har husket at udbetale dine lommepenge?",
  "push_connect_child_help_develop_economical_skills": "Når du opretter forbindelse til dit barn, hjælper du dit barn med at udvikle sine økonomiske færdigheder",
  "push_children_financial_smarter": "Børn nemt kan blive økonomisk ansvarlige! Hvad synes du om det?",
  "event_withdrawal_child": "{user.nickname} tog {transaction.str_value} fra {user.nickname} tilbage",
  "trustly_manual_transaction_email_subject": "Sådan! du har lige sendt {transaction.str_value} til {transaction.child.name} ?",
  "trustly_manual_transaction_email_body": "Fordi du har foretaget en enkel overførsel fra din konto til {transaction.child.name} -konto, kræver det ingen Mobile BankID-konto. Vi vil bare sikre os at du har foretaget en overførsel. Hvis dette er tilfældet, så ignorer blot denne email. Hvis dette ikke er tilfældet, vil vi bede dig om at kontrollere, om nogen har adgang til din telefon. Bemærk venligst, at enkelte overførsler kun kan foretages mellem de konti, du tidligere har knyttet til din BankID og vores troværdige partner. Du kan overføre maks. 2000kr per Overførsel per dag. Du kan se dine tilknyttede konti i appen under fanen Downloads.",
  "push_parent_not_giving_chores": "PLZ_TRANSLATE Få dine børn til at hjælpe hjemme! Giv en opgave til dit barn!",
  "push_event_request_money": "PLZ_TRANSLATE {kid_id} beder om flere penge ({amount})!",
  "push_event_request_money_title": "PLZ_TRANSLATE {child_name} beder om penge!",
  "push_interest_notification": "PLZ_TRANSLATE Nyt Gimi Interesse Niveau: {interest_rate}",
  "phone_number_verification_sms": "PLZ_TRANSLATE Bekræftelseskode: {code}",
  "request_pin_code_change_sms": "PLZ_TRANSLATE Din bekræftelseskode til ændring af din PIN-kode er: {code}",
  "push_instantor_successful_login": "Successfully gathered bank details!",
  "push_instantor_unsuccessful_login": "Gathering bank details was unsuccessful!",
  "push_instantor_login_timeout": "You did not approve the Login request on `MobiltBankId` in 2 minutes.",
  "event_connect_for_money": "Connect to get money",
  "event_create_dream": "Create your dream",
  "event_secure_account": "Secure your account",
  "event_allowance_tips": "Good to know about allowance",
  "event_earn_like_master": "How to earn like a master",
  "event_interest_tips": "Good to know about interest",
  "event_withdrawal_tips": "Good to know about withdrawals",
  "event_how_to_save": "How to save like a master",
  "event_how_to_spend": "How to spend like a master",
  "event_add_cravings": "Got any cravings? Add them!",
  "event_suggest_chore": "Suggest a chore",
  "event_send_invite_reminder": "Send invite reminder",
  "event_keep_account": "Connect to keep your account",
  "event_will_delete_account": "Your account will be deleted",
  "event_connect_children": "Connect your children",
  "event_you_are_teaching_grow": "You are teaching how to grow",
  "event_add_expense": "How to add an expense",
  "event_you_are_teaching_spend": "You are teaching how to spend",
  "event_you_are_teaching_earn": "You are teaching how to earn",
  "event_how_upcoming_payment": "How upcoming payment works",
  "event_set_allowance": "Set allowance",
  "event_add_chores": "Add chores",
  "event_add_deposit_to_savings": "Add a deposit to savings?",
  "event_help_connect": "Click here for help to connect",
  "event_connect_get_going": "Connect to get going",
  "connect_get_going": "Connect to get going",
  "push_connect_for_money": "No connection means no money in the loop - Set up your connection with your parents or other elders in the app!",
  "push_create_dream": "Create your dream and start growing money for the things you want!",
  "push_verify_phone": "Verify phone number",
  "push_suggest_chore": "No way to earn your own money? Suggest a chore!",
  "push_send_invite_reminder": "You have not got any response on your invitation. Send another one?",
  "push_keep_account": "You will loose your account if you don't connect. Send another invitation!",
  "push_will_delete_account": "Your account will be deleted within 24 hours. Rescue yourself from future bankrupcy by connecting to your parents!",
  "push_account_deleted": "Your account and information has been deleted. If you want to start over you are always welcome back!",
  "push_connect_children": "No connection means no money in the loop - Set up your connection with your children in the app!",
  "push_set_allowance": "How do you want to support {child_name} with money? Update your settings in the app!",
  "push_help_connect_child": "You have not connected to a child. Need any help? We are happy to help out!",
  "push_get_going": "Still no connection. We feel we are losing you even before we got started! Go to the app to connect a child you want to rescue from future bankrupcy!",
  "push_user_veckopengen_name_change": "Veckopengen dör!!! (aaa - panik, WTF, help me!!) Nej nej, lugn. Alltså, bara namnet. Vi döper om. Namnet blir Gimi.",
  "push_cloud_created": "PLZ_TRANSLATE Your cloud is created",
  "event_invitation_is_sent": "PLZ_TRANSLATE Invitation is sent",
  "event_you_are_connected": "PLZ_TRANSLATE You are connected!",
  "event_you_have_got_an_invitation": "PLZ_TRANSLATE You have got an invitation",
  "event_invitation_was_not_accepted": "PLZ_TRANSLATE Invitation was not accepted",
  "event_has_a_new_connection": "PLZ_TRANSLATE Has a new connection",
  "event_you_have_set_allowance": "PLZ_TRANSLATE You have set allowance",
  "event_changed_to_weekly_allowance": "PLZ_TRANSLATE Changed to weekly allowance",
  "event_changed_to_monthly_allowance": "PLZ_TRANSLATE Changed to monthly allowance",
  "event_allowance_settings_are_updated": "PLZ_TRANSLATE Allowance settings are updated",
  "event_allowance_amount_is_updated": "PLZ_TRANSLATE Allowance amount is updated",
  "event_birthday_today": "PLZ_TRANSLATE Birthday today!",
  "event_suggestion_of_new_allowance": "PLZ_TRANSLATE Suggestion of new allowance",
  "event_suggestion_of_new_chore_update": "PLZ_TRANSLATE Suggestion of new chore update",
  "event_suggestion_of_monthly_allowance": "PLZ_TRANSLATE Suggestion of monthly allowance",
  "event_chore_was_approved": "PLZ_TRANSLATE {chore.title} was approved",
  "event_chore_was_auto_approved": "PLZ_TRANSLATE {chore.title} was auto approved",
  "event_chore_was_disapproved": "PLZ_TRANSLATE {chore.title} was disapproved",
  "event_want_to_activate_auto_approval": "PLZ_TRANSLATE Want to activate auto approval?",
  "event_requests_for_chore_permission": "PLZ_TRANSLATE Requests for chore permission",
  "event_you_got_permission_to_edit_chores": "PLZ_TRANSLATE You got permission to edit chores",
  "event_you_gave_permission_to_edit_chores": "PLZ_TRANSLATE You gave permission to edit chores",
  "event_you_got_a_chore_suggestion": "PLZ_TRANSLATE You got a chore suggestion",
  "event_chore_was_deleted": "PLZ_TRANSLATE {chore} was deleted",
  "event_next_payment_is_added_to_cloud": "PLZ_TRANSLATE Next payment is added to cloud",
  "event_your_payment_to_cloud": "PLZ_TRANSLATE Your payment to cloud",
  "event_gimi_interest_is_changed_to_x": "PLZ_TRANSLATE Gimi interest is changed to x%",
  "event_shared_wishlist": "PLZ_TRANSLATE Shared wishlist",
  "event_report_last_week": "PLZ_TRANSLATE Report: Last week",
  "event_report_last_month": "PLZ_TRANSLATE Report: Last month",
  "event_yummy_a_new_update_is_available": "PLZ_TRANSLATE Yummy! A new update is available",
  "event_child_could_not_be_connected": "PLZ_TRANSLATE Child could not be connected",
  "event_allowance_is_set_for_you": "PLZ_TRANSLATE Allowance is set for you",
  "event_chore_was_not_approved": "PLZ_TRANSLATE {chore.title} was not approved",
  "event_reminder_of_chore": "PLZ_TRANSLATE Reminder of {chore}",
  "event_chore_is_deleted": "PLZ_TRANSLATE {chore.title} is deleted",
  "event_interest_rate_is_changed_to_x": "PLZ_TRANSLATE Interest rate is changed to {x}%",
  "event_create_a_new_dream": "PLZ_TRANSLATE Create a new dream",
  "event_withdrawal_made_from_your_cloud": "PLZ_TRANSLATE Withdrawal made from your cloud",
  "event_deposit_made_to_your_cloud": "PLZ_TRANSLATE Deposit made to your cloud",
  "event_share_your_cravings_for_your_birthday": "PLZ_TRANSLATE Share your cravings for your birthday",
  "event_share_your_cravings": "PLZ_TRANSLATE Share your cravings",
  "event_happy_birthday": "PLZ_TRANSLATE Happy birthday",
  "push_you_have_a_new_connection": "PLZ_TRANSLATE You have a new connection! ",
  "push_you_have_got_an_invitation_to_connect": "PLZ_TRANSLATE You have got an invitation from {connection_token.created_by.nickname} to connect",
  "push_allowance_is_set_for_you_check_it_out_in_the_app": "PLZ_TRANSLATE Allowance is set for you! Check it out in the app!",
  "push_child_has_completed_a_chore": "PLZ_TRANSLATE {assignment.child.name} has completed a chore!",
  "push_parent_name_asks_permission_to_edit_your_chores": "PLZ_TRANSLATE {name} asks permission to edit your chores",
  "push_name_received_x_in_allowance_from_you_today_mark_it_as_paid_out_if_you_paid_out_cash": "PLZ_TRANSLATE {chore} received {amount} in allowance from you today! Mark it as paid out if you paid out cash!",
  "push_child_has_reached_a_dream": "PLZ_TRANSLATE {name} has reached a dream",
  "event_add_email": "PLZ_TRANSLATE Add email for status & security",
  "push_short_tutorial": "PLZ_TRANSLATE That's how Gimi works, in 20 seconds",
  "event_chore_name_is_changed": "PLZ_TRANSLATE PLZ_CHECK Chore {chore.title} is changed",
  "event_welcome_back": "PLZ_TRANSLATE Welcome back! Do you want to start over?",
  "event_tell_that_your_back": "PLZ_TRANSLATE Let your family know you're back!",
  "event_parent_could_not_be_connected": "PLZ_TRANSLATE Föräldrar kunde inte anslutas",
  "event_you_made_a_withdrawal_parent": "PLZ_TRANSLATE Du gjorde ett uttag",
  "event_you_made_a_withdrawal_child": "PLZ_TRANSLATE {withdrawal.created_by.nickname} gjorde ett uttag",
  "event_has_created_a_new_dream_parent": "PLZ_TRANSLATE {goal.child.nickname} sparar nu till en ny dröm",
  "event_has_created_a_new_dream_child": "PLZ_TRANSLATE Du sparar nu till en ny dröm",
  "event_has_reached_a_dream_parent": "PLZ_TRANSLATE {goal.child.nickname} har sparat ihop till sin dröm",
  "event_has_reached_a_dream_child": "PLZ_TRANSLATE Duhar sparat ihop till sin dröm",
  "event_you_now_got_weekly_allowance_parent": "PLZ_TRANSLATE {allowance.child.nickname} får nu veckopeng av {allowance.parent.nickname}",
  "event_you_now_got_weekly_allowance_child": "PLZ_TRANSLATE Du får nu veckopeng av {relation.parent.nickname}",
  "event_you_now_got_monthly_allowance_parent": "PLZ_TRANSLATE {allowance.child.nickname} får nu månadspeng av {allowance.parent.nickname}",
  "event_you_now_got_monthly_allowance_child": "PLZ_TRANSLATE Du får nu månadspeng av {allowance.parent.nickname}",
  "event_you_have_got_a_new_chore_parent": "PLZ_TRANSLATE {child.nickname} har en ny uppgift",
  "event_you_have_got_a_new_chore_child": "PLZ_TRANSLATE Du har en ny uppgift",
  "event_you_have_got_x_new_chores_parent": "PLZ_TRANSLATE {child.nickname} har {x} nya uppgifter",
  "event_you_have_got_x_new_chores_child": "PLZ_TRANSLATE Du har {x} nya uppgifter",
  "event_you_have_got_an_interest_rate_of_x_parent": "PLZ_TRANSLATE {child.nickname} har fått en ränta i Molnet på {child.total_interest_rate}%",
  "event_you_have_got_an_interest_rate_of_x_child": "PLZ_TRANSLATE Du har fått en ränta i Molnet på {child.total_interest_rate}%",
  "event_you_have_reached_a_dream_parent": "PLZ_TRANSLATE {goal.child.nickname} har nått sin dröm",
  "event_you_have_reached_a_dream_child": "PLZ_TRANSLATE Du har nått din dröm",
  "event_done_with_chore_parent": "PLZ_TRANSLATE {assignment.child.nickname} är klar med {assignment.task.title}",
  "event_done_with_chore_child": "PLZ_TRANSLATE Du är klar med {assignment.task.title}"
}