{
  "push_child_transferred_to_savings": "{transaction.child.nickname} har opsparet {transaction.str_value}",
  "push_goal_created": "{goal.created_by.name} har oprettet opsparingsmålet {goal.title}",
  "push_goal_completed_child": "Du har opnået opsparingsmålet {goal.title}",
  "push_goal_completed_parent": "{goal.child.nickname} har opnået opsparingsmålet {goal.title}",
  "push_withdrawal_child": "{transaction.created_by.name} fratrukket {transaction.str_value} fra opsparing",
  "push_withdrawal_parent": "{transaction.created_by.name} fratrukket {transaction.str_value} fra {transaction.child.nickname}",
  "push_timed_assignment_expired": "Du nåede det desværre ikke {assignment.task.title}",
  "push_connected_with_parent": "Du er forbundet med en tilhænger!",
  "push_invite_accepted": "{user} har lige accepteret din indbydelse",
  "push_assignment_created": "Yihaa! Du har fået en ny opgave",
  "push_assignment_active_again": "Opgaven {assignment.task.title} er tilgængelig igen. Først til mølle",
  "push_assignment_done": "{assignment.child.nickname} har lige udført {assignment.task.title}",
  "push_assignment_done_by_other": "Du var ikke hurtig nok! {assignment.task.shared_task_completed_by} udførte {assignment.task.title} før dig",
  "push_assignment_rejected": "{assignment.task.title} blev ikke godkendt af {rejected_by.nickname}",
  "push_assignment_approved": "{assignment.task.title} blev godkendt af {assignment.approved_by.nickname}",
  "push_insertion_by_other": "Nice! {transaction.created_by.name} har lige sat {transaction.str_value} ind på din sparegris",
  "event_payday_interest": "Næste betaling er blevet tilføjet til din opsparing",
  "event_payday_chore_reward": "Næste betaling er blevet tilføjet til din opsparing",
  "push_account_select_started": "Registrering af bankkonto er i gang",
  "push_parent_account_selected": "Din bankkonto er aktiveret",
  "push_child_account_selected": "{child.nickname}s bankkonto er aktiveret",
  "push_weekly_trustly_payout_failed_parent": "Overførelse af {transaction.parent.nickname}s ugentlige lommepenge mislykkedes",
  "push_monthly_trustly_payout_failed_parent": "Overførelse af {transaction.parent.nickname}s månedlige lommepenge mislykkedes",
  "push_weekly_trustly_payout_trustly_failed_child": "Overførelse af dine ugentlige lommepenge mislykkedes",
  "push_monthly_trustly_payout_trustly_failed_child": "Overførelse af dine månedlige lommepenge mislykkedes",
  "push_changed_to_weekly_allowance": "{name} er gået over til ugepenge",
  "push_changed_to_monthly_allowance": "{name} er gået over til månedspenge",
  "push_trustly_weekly_allowance_parent_changed": "Nu betales {child}s ugentlige lommepenge fra din konto",
  "push_trustly_monthly_allowance_parent_changed": "Nu betales {child}s månedlige lommepenge fra din konto",
  "push_trustly_weekly_allowance_parent_changed_2": "Nu udbetales {child} s ugentlige ydelse fra {parent}  s konto",
  "push_trustly_monthly_allowance_parent_changed_2": "Nu udbetales {child} s månedlige ydelse fra {parent}  s konto",
  "push_trustly_weekly_allowance_parent_changed_child": "Nu er din ugentlige ydelse udbetalt til din bankkonto hver uge",
  "push_trustly_monthly_allowance_parent_changed_child": "Nu er din månedlig ydelse udbetalt til din bankkonto hver måned",
  "dashboard_interest_added": "Fik {transaction.str_value} i opsparingsbonus",
  "dashboard_changed_to_weekly_allowance": "Er gået over til ugentlige lommepenge",
  "dashboard_changed_to_monthly_allowance": "Er gået over til månedlige lommepenge",
  "trustly_charge_over_limit_email_subject": "Vigtig meddelelse om udbetaling",
  "trustly_charge_failed_email_subject": "Meddelelse om mislykket udbetaling",
  "trustly_payout_failed_email_subject": "Meddelelse om mislykket udbetaling og tilbagebetaling",
  "invite_email_subject": "Inviter til Gimi",
  "login_email_subject": "Log ind på Gimi",
  "push_trustly_over_limit": "Mislykket overførsel på {amount}",
  "dashboard_goal_created": "Oprettede opsparingsmål {goal.title}",
  "dashboard_goal_completed": "Opsparingsmålet er opnået {goal.title}",
  "dashboard_transfer_to_savings": "Opsparet {transaction.str_value}",
  "event_complete_card_order": " Et kort er på vej! Du vil modtage et kort fra Gimi. Åbn appen for mere info",
  "push_task_updated": "{user} har ændret opgaven {task}",
  "dashboard_child_not_connected": "Glem ikke at tilslutte dig",
  "dashboard_child_setup": "Er ikke færdigoprettet endnu",
  "dashboard_weekly_allowance_over_trustly_limit": "Ugentlige lommepenge er over beløbsgrænsen",
  "dashboard_monthly_allowance_over_trustly_limit": "Månedlige lommepenge er over beløbsgrænsen",
  "dashboard_failed_trustly_transaction": "Mislykket overførsel",
  "dashboard_completed_trustly_transaction": "{transaction.str_value} overførtes til bankkonto",
  "dashboard_assignment_completed": "Klar med {assignment.task.title}",
  "dashboard_child_trustly_account_ongoing": "Afventer tilslutning til bankkontoen",
  "dashboard_goal_archived": "Arkiverede opsparingsmålet {goal.title}",
  "dashboard_child_trustly_allowance_enabled": "Overførsler aktiverede",
  "dashboard_add_trustly_account": "Tilføj bankkonto",
  "push_first_wish_created": "{wish.child.nickname} har oprettet ønskeseddel og har anmodet om en {wish.title}",
  "push_wish_created": "{wish.child.nickname} har tilføjet {wish.title} til ønskelisten",
  "push_wish_deleted": "{wish.child.nickname} har slettet {wish.title} fra ønskelisten",
  "push_child_logged_in": "{child.nickname} er logget på",
  "sms_app_download": "Velkommen til Ugepenge!\n http//onelink.to/t69wn8",
  "push_goal_archived": "{goal.updated_by.name} gemte opsparingsmålet {goal.title}",
  "push_timed_assignment_created": "Gå ind og kig, du har fået en tidsbegrænset opgave",
  "push_shared_assignment_created": "Kig ind i appen, du konkurrerer om at fuldføre en opgave",
  "push_repeating_assignment_created": "Kig ind! Du har en ny opgave, som kan gentages",
  "push_check_wish_list": "En måned tilbage til din fødselsdag. Tjek ønskelisten",
  "push_assignment_approved_parent": "{assignment.approved_by.name} godkendte opgaven {assignment.task.title}. ({assignment.str_value})",
  "dashboard_assignment_approved": "Opgaven {assignment.task.title} blev godkendt. ({assignment.str_value})",
  "push_task_enabled": "Nu kan du udføre opgaven {task}",
  "push_disabled_task_created": "{child} har foreslået opgave {task}",
  "push_weekly_payout_message_parent": "{transaction.str_value} af ugentlige ydelse blev overført til {transaction.child.nickname} s bankkonto",
  "push_monthly_payout_message_parent": "{transaction.str_value} af den månedlig ydelse blev overført til {transaction.child.nickname} s bankkonto",
  "push_charge_message_parent": "I øjeblikket overføres {amount} til {child} bankkonto i morgen",
  "dashboard_disabled_task_created": "Foreslået opgave {task}",
  "push_trustly_mandate_revoked": "Din bankkonto er nu deaktiveret, opdater dine oplysninger for at bruge bankoverførsler",
  "push_weekly_allowance_pre_payout_parent_0": "Tid til {child}s ugentlige lommepenge",
  "push_weekly_allowance_pre_payout_parent_1": "Tid til {child}s ugentlige lommepenge",
  "push_weekly_allowance_pre_payout_parent_2": "Tid til {child}s ugentlige lommepenge",
  "push_weekly_allowance_pre_payout_parent_3": "Tid til {child}s ugentlige lommepenge",
  "push_weekly_allowance_pre_payout_parent_4": "Tid til {child}s ugentlige lommepenge",
  "push_monthly_allowance_pre_payout_parent_0": "Tid til {child}s månedlige lommepenge",
  "push_monthly_allowance_pre_payout_parent_1": "Tid til {child}s månedlige lommepenge",
  "push_monthly_allowance_pre_payout_parent_2": "Tid til {child}s månedlige lommepenge",
  "push_monthly_allowance_pre_payout_parent_3": "Tid til {child}s månedlige lommepenge",
  "push_monthly_allowance_pre_payout_parent_4": "Tid til {child}s månedlige lommepenge",
  "push_weekly_assignment_0": "I dag, kan du {task} for {value}, fedt!",
  "push_weekly_assignment_1": "Godmorgen venner! I dag kan du tjene {value}! Gå ind i appen og se hvilken opgave du kan udføre",
  "push_weekly_assignment_2": "Du har modtaget en ny opgave: {task} Gå ind i appen og tjek hvad du kan tjene",
  "push_weekly_assignment_3": "Ny opgave! Yay! Du kan blive {value} rigere! Gå ind i appen og tjek hvilke opgaver du kan udføre",
  "push_weekly_assignment_4": "Ny opgave! {task} Box! Gå ind i appen og se, hvad du kan tjene",
  "push_weekly_allowance_trustly_pre_payout": "Udbetaling i morgen.  Lige nu er der {amount} i ugentlige ydelse til {child}s bankkonto",
  "push_monthly_allowance_trustly_pre_payout": "Udbetaling i morgen. Lige nu er der {amount} i månedlige ydelse til {child}s bankkonto",
  "push_weekly_interest_added_0": "Tillykke! Ugens opsparingsbonus er lagt i sparegrisen",
  "push_weekly_interest_added_1": "Tillykke! Ugens opsparingsbonus er lagt i sparegrisen",
  "push_weekly_interest_added_2": "Tillykke! Ugens opsparingsbonus er lagt i sparegrisen",
  "push_weekly_interest_added_3": "Tillykke! Ugens opsparingsbonus er lagt i sparegrisen",
  "push_weekly_interest_added_4": "Tillykke! Ugens opsparingsbonus er lagt i sparegrisen",
  "push_monthly_interest_added_0": "Tillykke! Månedens opsparingsbonus er lagt i sparegrisen",
  "push_monthly_interest_added_1": "Tillykke! Månedens opsparingsbonus er lagt i sparegrisen",
  "push_monthly_interest_added_2": "Tillykke! Månedens opsparingsbonus er lagt i sparegrisen",
  "push_monthly_interest_added_3": "Tillykke! Månedens opsparingsbonus er lagt i sparegrisen",
  "push_monthly_interest_added_4": "Tillykke! Månedens opsparingsbonus er lagt i sparegrisen",
  "push_new_weekly_tasks_0": "Kig! Du har fået nye opgaver",
  "push_new_weekly_tasks_1": "Kig! Du har fået nye opgaver",
  "push_new_weekly_tasks_2": "Kig! Du har fået nye opgaver",
  "push_new_weekly_tasks_3": "Kig! Du har fået nye opgaver",
  "push_new_weekly_tasks_4": "Kig! Du har fået nye opgaver",
  "push_goal_activated": "{goal.updated_by.name} har oprettet et opsparingsmål {goal.title}",
  "push_goal_sponsored": "{goal.updated_by.name} har sponsoreret opsparingsmålet {goal.title}",
  "push_goal_boost_decreased": "Du har mistet et boost på dit opsparingsmål",
  "push_goal_boosts_decreased": "Du har mistet boosts på dit opsparingsmål",
  "dashboard_goal_boost_decreased": "Mistet et boost på opsparingsmålskortet",
  "dashboard_goal_boosts_decreased": "Mistet boosts på opsparingsmålskortet",
  "push_goal_almost_completed": "Godt arbejde! Du er næsten færdig med dit opsparingsmål",
  "push_duration_assignment_created": "Du har fået en ny opgave!",
  "event_task_created": "{task.created_by.name} oprettet opgave: {task.title}",
  "event_task_updated": "{user.nickname} opdateret opgave: {task.title}",
  "event_task_suggested": "{task.created_by.name} foreslået opgave: {task.title}",
  "event_task_deleted": "{user.nickname} fjernet opgave: {task.title}",
  "event_assignment_rejected": "{user.nickname} afvist opgave: {assignment.task.title}",
  "event_assignment_approved": "{assignment.approved_by.name} godkendt opgave: {assignment.task.title}",
  "event_assignment_expired": "{assignment.child.nickname} lykkedes ikke at fuldføre opgaven: {assignment.task.title} i tide",
  "event_assignment_completed_by_other": "{assignment.task.shared_task_completed_by} gennemførte opgaven {assignment.task.title} først",
  "event_goal_created": "{goal.created_by.name} oprettet opsparingsmål {goal.title}",
  "event_goal_updated": "{goal.updated_by.name} opdateret opsparingsmål {goal.title}",
  "event_goal_deleted": "{user.nickname} fjernet opsparingsmål {goal.title}",
  "event_goal_completed": "{goal.child.nickname} gennemført opsparingsmål {goal.title}",
  "event_wish_created": "{wish.child.nickname} tilføjede et nyt ønske: {wish.title}",
  "event_wish_updated": "{wish.updated_by.name} opdateret ønske: {wish.title}",
  "event_wish_deleted": "{user.nickname} fjernet ønske: {wish.title}",
  "event_birthday": "{child.nickname} fødselsdag i dag",
  "event_assignment_reminder": "{parent.nickname} lige sendt dig en påmindelse til {assignment.task.title}",
  "push_assignment_reminder": "{parent.nickname} lige sendt dig en påmindelse til {assignment.task.title}",
  "push_new_app_version": "En ny opdatering kommer i appstore",
  "push_manual_trustly_withdrawal": "{transaction.str_value} er overført til {transaction.child.nickname} s bankkonto",
  "push_manual_trustly_withdrawal_failed_parent": "Overførslen af {transaction.str_value} til {transaction.child.nickname} s bankkonto ugentlige ydelse var mislykket",
  "push_manual_trustly_withdrawal_failed_child": "Overførsel af {transaction.str_value} til din bankkonto mislykkedes",
  "push_event_message_created": "{user.nickname}: \"{text}\"",
  "push_assignment_auto_approved": "Flot! {assignment.task.title} blev automatisk godkendt",
  "push_assignment_auto_approved_parent": "Opgave er automatisk godkendt: {assignment.task.title}",
  "event_assignment_auto_approved": "Opgaven er automatisk godkendt: {assignment.task.title}",
  "dashboard_connected_parent": "Du er nu forbundet med {child.nickname}",
  "push_before_super_parent": "Du er ved at blive en super forælder! Bliv forbundet med dit barn...",
  "push_intro_chores": "Vi er glade for at have dig ombord. Kom i gang med opgaver!",
  "push_intro_make_deposit": "Det er tid til at digitalisere dine børns penge. Tilføj alle kontanter til Opsparing!",
  "push_reminder_give_chores": "Glem ikke at give dine børn opgaver så de kan tjene nogle ekstra penge, samtidig med at de lærer hvordan penge fungerer. Find eksempelopgaver i appen",
  "push_suggest_task": "Vidste du, at du kan foreslå opgaver?",
  "push_exchange_cash": "Har du kontanter? Giv det til dine forældre og bede dem om at føje pengene til din opsparing",
  "push_weekly_allowance_pre_payout_0": "I dag fik {child} hans ugentlige sats i sin spargris!",
  "push_weekly_allowance_pre_payout_1": "{child} har fået sin ugentlige ydelse i dag!",
  "push_weekly_allowance_pre_payout_2": "{child} s lommepenge er blevet overført til sparegrisen, klirr!",
  "push_weekly_allowance_pre_payout_3": "Payday! {child} har fået den ugentlige ydelse overført til sin sparegris!",
  "push_weekly_allowance_pre_payout_4": "Payday! {child} s ugentlige ydelse er blevet overført til sparegrisen!",
  "push_monthly_allowance_pre_payout_0": "I dag har {child} fået sine månedlige lommepenge overført til sin sparegris!",
  "push_monthly_allowance_pre_payout_1": "{child} har modtaget sine månedlige lommepenge i dag!",
  "push_monthly_allowance_pre_payout_2": "{child}s månedlige lommepenge er blevet tilføjet til Opsparing!",
  "push_monthly_allowance_pre_payout_3": "Payday! {child}s månedlige lommepenge er blevet tilføjet til Opsparing!",
  "push_monthly_allowance_pre_payout_4": "{child}a månedlige lommepenge er blevet tilføjet til Opsparing!",
  "push_remind_parent_child_weekly_money": "Vidste du, at hvis du er tilsluttet med dine forældre, vil de hver uge blive mindet om, om de har husket at udbetale dine lommepenge?",
  "push_connect_child_help_develop_economical_skills": "Når du opretter forbindelse til dit barn, hjælper du dit barn med at udvikle sine økonomiske færdigheder",
  "push_children_financial_smarter": "Børn kan nemt blive klogere økonomisk! Lær hvordan!",
  "event_withdrawal_child": "{user.nickname} fratrukket {transaction.str_value} fra opsparing",
  "trustly_manual_transaction_email_subject": "Sådan! du har lige sendt {transaction.str_value} til {transaction.child.nickname} ?",
  "trustly_manual_transaction_email_body": "Fordi du har foretaget en enkel overførsel fra din konto til {transaction.child.nickname} -konto, kræver det ingen Mobile BankID-konto. Vi vil bare sikre os at du har foretaget en overførsel. Hvis dette er tilfældet, så ignorer blot denne email. Hvis dette ikke er tilfældet, vil vi bede dig om at kontrollere, om nogen har adgang til din telefon. Bemærk venligst, at enkelte overførsler kun kan foretages mellem de konti, du tidligere har knyttet til din BankID og vores troværdige partner. Du kan overføre maks. 2000kr per Overførsel per dag. Du kan se dine tilknyttede konti i appen under fanen Downloads.",
  "push_parent_not_giving_chores": "Få dine børn til at hjælpe derhjemme! Giv opgaver ud!",
  "push_event_request_money": "{kid_id} beder om flere penge ({amount})!",
  "push_event_request_money_title": "{child_name} beder om penge!",
  "push_interest_notification": "Ny Gimi Rentesats: {interest_rate}",
  "phone_number_verification_sms": "Bekræftelseskode: {code}",
  "request_pin_code_change_sms": "Din bekræftelseskode til ændring af din PIN-kode er: {code}",
  "push_instantor_successful_login": "Det er lykkedes at indsamle dine bankoplysninger!",
  "push_instantor_unsuccessful_login": "Det mislykkedes at indsamle dine bankoplysninger!",
  "push_instantor_login_timeout": "Du godkendte ikke login anmodningen på `MobiltBankId` på 2 minutter.",
  "event_connect_for_money": "PLZ_TRANSLATE No supporters, no money. Invite a parent!",
  "event_create_dream": "Opret din drøm",
  "event_secure_account": "Sikre din konto",
  "event_allowance_tips": "Godt at vide om lommepenge",
  "event_earn_like_master": "Sådan kan du tjene godt",
  "event_interest_tips": "Godt at vide om renter",
  "event_withdrawal_tips": "Godt at vide om fratrækninger",
  "event_how_to_save": "Sådan sparer du godt op",
  "event_how_to_spend": "Sådan bruger du bedst penge",
  "event_add_cravings": "Har du trang til noget? Tilføj dem!",
  "event_suggest_chore": "PLZ_TRANSLATE Start earning extra money... Suggest a chore!",
  "event_keep_account": "Opret forbindelse for at beholde din konto",
  "event_will_delete_account": "Din konto vil blive slettet",
  "event_connect_children": "Forbind dine børn",
  "event_you_are_teaching_grow": "Du lærer, hvordan man kan vækste",
  "event_add_expense": "Hvordan tilføjer man en udgift",
  "event_you_are_teaching_spend": "Du lærer, hvordan man forbruger",
  "event_you_are_teaching_earn": "Du lærer, hvordan man tjener",
  "event_how_upcoming_payment": "Hvordan kommende betalinger virker",
  "event_set_allowance": "Sæt lommepenge",
  "event_add_chores": "tilføj opgaver",
  "event_help_connect": "Klik her for at få hjælp til at oprette forbindelse",
  "event_connect_get_going": "Opret forbindelse for at komme igang",
  "connect_get_going": "Opret forbindelse for at komme igang",
  "push_connect_for_money": "Ingen forbindelse betyder ingen penge i loopet - Opret forbindelse til dine forældre eller andre ældre i appen!",
  "push_create_dream": "Start med at spare op til en drøm!",
  "push_verify_phone": "Bekræft dit telefonnummer, så du kan logge ind!",
  "push_suggest_chore": "Vil du tjene nogle penge? Foreslå en opgave i appen!",
  "push_send_invite_reminder": "Din invitation er endnu ikke accepteret ... Send en påmindelse?",
  "push_keep_account": "Gimi virker ikke uden forbindelse. Send en invitation!",
  "push_will_delete_account": "Din konto vil blive slettet om 24 timer, hvis du ikke opretter forbindelse til en voksen.",
  "push_account_deleted": "Din konto og oplysninger er blevet slettet. Hvis du vil starte forfra, er du altid velkommen tilbage!",
  "push_connect_children": "Ingen forbindelse betyder ingen penge i loopet- Opret forbindelse til dine børn i appen!",
  "push_set_allowance": "Hvordan vil du støtte {child_name} med penge? Opdater dine indstillinger i appen!",
  "push_help_connect_child": "Du er ikke forbundet med nogen. Brug for hjælp?",
  "push_get_going": "Stadig ingen forbindelser...Vil du lære nogle børn om penge?",
  "push_user_veckopengen_name_change": "Veckopengen dör!!! (aaa - panik, WTF, help me!!) Nej nej, lugn. Alltså, bara namnet. Vi döper om. Namnet blir Gimi.",
  "push_cloud_created": "Din Sky er oprettet",
  "event_invitation_is_sent": "Invitationen er sendt",
  "event_you_are_connected_receiver": "Du er forbundet med {connection_token.created_by.nickname}",
  "event_you_are_connected_sender": "Du er forbundet med {connection_token.used_by.nickname}",
  "event_you_have_got_an_invitation": "Du har fået en invitation fra {connectiontoken.created_by.nickname}",
  "event_invitation_was_not_accepted": "Invitation blev ikke accepteret",
  "event_has_a_new_connection": "Har en ny forbindelse",
  "event_changed_to_weekly_allowance": "Ændret til ugentlige lommepenge",
  "event_changed_to_monthly_allowance": "Ændret til månedlige lommepenge",
  "event_allowance_amount_is_updated": "Lommepenge beløbet er opdateret",
  "event_birthday_today": "Fødselsdag i dag!",
  "event_suggestion_of_new_chore_update": "Forslag til ny opgave opdatering",
  "event_suggestion_of_monthly_allowance": "Forslag til månedlige lommepenge",
  "event_chore_was_auto_approved": "{chore.title} blev automatisk godkendt",
  "event_chore_was_disapproved": "{chore.title} blev ikke godkendt",
  "event_want_to_activate_auto_approval": "Vil du aktivere automatisk godkendelse?",
  "event_requests_for_chore_permission": "Anmodninger for opgave tilladelse",
  "event_you_got_permission_to_edit_chores": "Du har fået tilladelse til at redigere opgaver",
  "event_you_gave_permission_to_edit_chores": "Du har givet tilladelse til at redigere opgaver",
  "event_you_got_a_chore_suggestion": "Du har et {child.nickname} fra {child.nickname}",
  "event_chore_was_deleted": "{chore} blev slettet",
  "event_next_payment_is_added_to_cloud": "Næste betaling er blevet tilføjet i skyen",
  "event_your_payment_to_cloud": "Din betaling til skyen",
  "event_gimi_interest_is_changed_to_x": "Gimi renten er ændret til x%",
  "event_shared_wishlist": "Delte ønskelisten",
  "event_report_last_week": "Rapport: Sidste uge",
  "event_report_last_month": "Rapport: Sidste måned",
  "event_yummy_a_new_update_is_available": "Juhuu! En ny opdatering er tilgængelig!",
  "event_child_could_not_be_connected": "Der kunne ikke oprettes forbindelse til barnet",
  "event_chore_was_not_approved": "{rejected_by.nickname} har afslået {chore.title}",
  "event_reminder_of_chore": "Påmindelse for {chore.title}",
  "event_chore_is_deleted": "{chore.title} er slettet",
  "event_interest_rate_is_changed_to_x": " Renten er ændret til {x}%",
  "push_create_new_dream": "Opret en ny drøm",
  "event_withdrawal_made_from_your_cloud": "{parent.nickname} fratrukket fra din opsparing.",
  "event_deposit_made_to_your_cloud": "{parent.nickname} tilføjet til din opsparing",
  "event_share_your_cravings_for_your_birthday": "Del dine cravings for din fødselsdag",
  "event_share_your_cravings": "Del dine cravings",
  "event_happy_birthday": "Tillykke med fødselsdagen",
  "push_you_have_a_new_connection": "Du har en ny forbindelse! ",
  "push_you_have_got_an_invitation_to_connect": "Du har en invitation fra {connectiontoken.created_by.nickname} til at oprette forbindelse",
  "push_allowance_is_set_for_you_check_it_out_in_the_app": "Dine lommepenge er sat op! Tjek det ud i appen!",
  "push_parent_name_asks_permission_to_edit_your_chores": "{name} beder om tilladelse til at redigere dine opgaver",
  "push_payday_parent": "Payday for {child.nickname}. Tjek hvor mange penge der blev tilføjet til Opsparingen!",
  "push_child_has_reached_a_dream": "{child.nickname} har nået en drøm",
  "event_add_email": "Tilføj e-mail for status og sikkerhed",
  "event_chore_title_or_amount_changed": "{parent.nickname} har opdateret {chore.title}",
  "event_welcome_back": "Velkommen tilbage! Vil du starte forfra?",
  "event_tell_that_your_back": "Lad din familie vide, at du er tilbage!",
  "event_parent_could_not_be_connected": "Der kunne ikke oprettes forbindelse til dine forældre",
  "event_you_made_a_withdrawal_parent": "Du har lavet et fratrækning",
  "event_you_made_a_withdrawal_child": "{withdrawal.created_by.nickname} har lavet en fratrækning",
  "event_has_created_a_new_dream_parent": "{goal.child.nickname} er ved at spare op til en ny drøm",
  "event_has_created_a_new_dream_child": "Du sparer op til en ny drøm",
  "event_has_reached_a_dream_parent": "{goal.child.nickname} har opnået sin drøm",
  "event_has_reached_a_dream_child": "Du har opnået din drøm",
  "event_you_now_got_weekly_allowance_parent": "{allowance.child.nickname} vil nu få ugentlige lommepenge fra {allowance.parent.nickname}",
  "event_you_now_got_weekly_allowance_child": "Du får nu ugentlige lommepenge fra {allowance.parent.nickname}",
  "event_you_now_got_monthly_allowance_parent": "{allowance.child.nickname} vil nu få månedlige lommepenge fra {allowance.parent.nickname}",
  "event_you_now_got_monthly_allowance_child": "Du får nu månedlige lommepenge fra {allowance.parent.nickname}",
  "event_you_have_got_a_new_chore_parent": "{user.nickname} har en ny opgave",
  "event_you_have_got_a_new_chore_child": "{user.nickname} har sendt dig en ny opgave",
  "event_you_have_got_x_new_chores_parent": "{child.nickname} har {x} nye opgaver",
  "event_you_have_got_x_new_chores_child": "{parent.nickname} har sent dig {x} nye opgaver",
  "event_you_have_got_an_interest_rate_of_x_parent": "{child.nickname} har en rente på {child.total_interest_rate}% i skyen",
  "event_you_have_got_an_interest_rate_of_x_child": "Du har fået en rentesats på {child.total_interest_rate}% i skyen",
  "event_done_with_chore_parent": "{assignment.child.nickname} er færdig med {assignment.task.title}",
  "event_done_with_chore_child": "Du er færdig med {assignment.task.title}",
  "push_tell_that_your_back": "{user.nickname} er tilbage i appen!",
  "push_payday_child": "Payday! Du har lige fået dine penge!",
  "push_received_first_money": "Du har modtaget dine første penge!",
  "push_suggest_chore_to_parents": "Vil du tjene penge? Foreslå en opgave til dine forældre!",
  "push_x_days_until_payday": "Du har {x} dage til Payday! Tjen flere penge og lav nogle af dine opgaver!",
  "push_checkout_balance": "Tjek din opsparing og se om dine penge vokser!",
  "push_have_you_bought_something": "Har du købt noget til {child.nickname} i dag? Lav en fratrækning fra opsparingen!",
  "push_does_kid_has_cash": "Har {child.nickname} kontanter? Tilføj det til opsparingen i appen istedet!",
  "push_need_help_with_dinner": "Har du brug for hjælp med aftensmaden? ATilføj en opgave for {child.nickname}",
  "event_has_card_arrived": "Er dit kort ankommet?",
  "event_pfs_card_blocked_by_parent": "Dit kort er blevet blokeret",
  "event_pfs_card_unblocked_by_parent": "Blokeringen af dit kort er blevet fjernet",
  "push_pfs_card_blocked_by_parent": "Dit kort er blevet blokeret af {pfs_card.updated_by.nickname}",
  "push_pfs_card_unblocked_by_parent": "Blokeringen af dit kort er blevet fjernet af {pfs_card.updated_by.nickname}",
  "event_pfs_manual_deposit_to_savings": "Du har modtaget en indbetaling fra {pfs_payment_target.payment.parent.nickname}",
  "event_pfs_payday_deposit_to_savings": "Du har modtaget en indbetaling på din konto",
  "push_pfs_manual_deposit_to_savings": "Du har modtaget en indbetaling fra {pfs_payment_target.payment.parent.nickname}",
  "push_pfs_payday_deposit_to_savings": "Du har modtaget en indbetaling på din konto",
  "event_payday_child": "Payday!",
  "event_payday_parent": "Payday for {child.nickname}",
  "event_premium_payday_child": "Payday!",
  "push_you_got_a_chore_suggestion": "Opgave foreslag fra {task.created_by.nickname}",
  "event_child_created": "Lær Gimi at kende!",
  "event_child_lost_the_card": "{child.nickname} har markeret kortet som mistet",
  "event_other_parent_asks_for_deposit": "{parent.nickname} anmoder om tilladelse til at indbetale til {child.nickname}",
  "event_new_weekly_tasks": "Tjek denne uges opgaver ud!",
  "event_permissions_to_deposit_granted": "Du har tilladelse til at sende penge til {child.nickname}",
  "event_suggested_chore_enabled": "{parent.nickname} har accepteret din foreslåede opgave!",
  "push_new_pfs_transaction_statement_child": "💳 Du har lige brugt {pfstransactionstatement.str_amount} på {pfstransactionstatement.merchant_name}",
  "push_new_pfs_transaction_statement_parent": "{statement.card.user.nickname} har lige brugt {statement.str_amount} på {statement.merchant_name}",
  "push_you_have_reached_a_dream": "Tillykke! Du har lige opnået din drøm! 🚀",
  "push_new_weekly_tasks": "Tjek ugens opgaver ud!",
  "push_turn_on_notifications": "Du går glip af vigtige events. Slå pushnotikationer til!",
  "event_turn_on_notifications": "Du går glip af vigtige beskeder. Tænd pushnotifikationer?",
  "push_connect_more_children": "Forbindelsesanmodning fra {child.nickname}",
  "one_off_push_parent": "Happy weekend! You are a super parent ✨",
  "one_off_push_child": "Happy weekend! Piggy loves you 💖",
  "push_connect_with_child": "Bliv forbundet til et barn! Gimi er sjovere med børn!",
  "push_child_card_activated": "{child.nickname} har lige aktiveret Gimi kortet! 👏",
  "event_card_has_been_activated": "{child.nickname} har lige aktiveret Gimi kortet! 👏",
  "push_declined_purchases_with_insufficient_funds": "🚫 Der er ikke nok penge på Gimi Kortet! Derfor blev dit køb hos {pfstransactionstatement.merchant_name} ikke godkendt. Vil du overføre penge til kortet?",
  "push_declined_purchases_with_blocked_card": "🚫 Dit Gimi kort er blokeret, derfor blev det ikke godkendt hos {pfstransactionstatement.merchant_name}.",
  "event_card_sign_up": "Fortsæt med kort registrering",
  "event_child_receive_money_from_other": "Lad {child.nickname} modtage penge fra andre kontakter!",
  "event_end_real_money": "Du kan nu sende rigtige penge til {child.nickname}!",
  "event_not_paid_premium_subscription": "Du har ikke betalt premiumabonnement",
  "push_not_paid_premium_subscription": "Tid til at betale dig Gimi abonnement...",
  "push_not_paid_premium_subscription_app": "Du skal betale for din premiumabonnement.",
  "event_reminder_of_premium_payment": "Påmindelse om at betale tilmeldingsgebyr",
  "event_subscription_not_paid_card_will_blocked": "Dit abonnement er ikke blevet betalt, kortet bliver blokeret i morgen!",
  "push_subscription_not_paid_card_will_blocked": "Premiumabonnement er ikke betalt. Gimi kortet bliver låst om 24 timer",
  "event_subscription_not_paid_card_blocked": "Dit abonnement er ikke blevet betalt, Gimi kortet er blevet blokeret.",
  "event_card_has_arrived": "Har du modtaget dit kort? Aktiver det!",
  "event_transfer_money_to_card": "Du har penge på din konto! Vil du bruge dem? Bare overfør til dit kort.",
  "event_name_blocked_your_card": "{parent.nickname} har blokeret dit kort",
  "push_name_blocked_your_card": "Dit kort er blevet blokeret af {parent.nickname}",
  "event_name_unblocked_your_card": "{parent.nickname} har blokeret dit kort",
  "push_name_unblocked_your_card": "Dit kort er blevet aktiveret af {parent.nickname}",
  "push_today_pay_day": "I dag er payday! 🎉",
  "event_today_pay_day": "I dag er payday!",
  "push_name_deposit_to_account": "Du har modtaget en indbetaling af {parent.nickname}",
  "event_name_deposit_to_account": "{parent.nickname} har lavet en indbetaling til din konto",
  "event_name_made_deposit_to_account": "{parent.nickname} har lavet en indbetaling til din konto",
  "push_name_made_deposit_to_account": "Du har modtaget en indbetaling i din opsparing",
  "push_give_chores_to_children": "Husk opgaver! Det lærer børn om at tjene penge!",
  "push_verify_phone_to_custom_account": "Verificer telefonnummer",
  "push_chores_waiting": "Du har {x} opgaver der venter. Få tjent nogle penge!",
  "event_add_card": "Tilføj dit betalingskort, så du kan foretage indbetalinger til dine børn!",
  "event_child_spend": "💳 Du har lige brugt {pfstransactionstatement.str_amount} hos {pfstransactionstatement.merchant_name}",
  "event_got_money_back": "Du har fået nogle penge tilbage fra {statement.merchant_name}",
  "push_got_money_back": "💰Du har lige fået nogle penge tilbage fra {statement.merchant_name}!",
  "push_enter_token_and_log_in": "Hej {{ user.name }}, Indtast koden {{ token.code }} i appen eller klik på knappen nedenfor for at logge ind. Vi ses i appen! 👋",
  "event_exceed_daily_limit": "{child.nickname} har lige overskredet den daglige udgiftsgrænse!",
  "push_exceed_daily_limit": "💸 {child.nickname} har lige overskredet den daglige udgiftsgrænse!",
  "event_exceed_weekly_limit": "{child.nickname} har lige overskredet den ugentlige udgiftsgrænse!",
  "push_exceed_weekly_limit": "{child.nickname} har lige overskredet den ugentlige udgiftsgrænse!",
  "event_exceed_monthly_limit": "{child.nickname} har lige overskredet den månedlige udgiftsgrænse!",
  "push_exceed_monthly_limit": "{child.nickname} har lige overskredet den månedlige udgiftsgrænse!",
  "event_pfs_payday": "Det er payday for {child.nickname}! ",
  "push_subscription_not_paid_card_blocked": "Gimi kortet er lukket ned. Betal abonnementsgebyr for {child.nickname} for at aktiveret det.",
  "verify_email_subject": "Bekræft din e-mail adresse",
  "push_add_profile_pic": "-",
  "event_you_are_connected": "Du er nu forbundet med {child.nickname}!",
  "push_card_purchase_decline": "Et kort køb blev afvist på grund af lav balance!",
  "event_how_premium_work": "Hvordan Premium virker",
  "push_card_decline_unlock": "🚫Dit Gimi kort er blokeret! Derfor blev det afslået hos {pfstransactionstatement.merchant_name}!",
  "push_next_payment_is_added_to_cloud": "Payday! Penge er blevet tilføjet til din opsparing! Tjek ud hvor meget i appen",
  "event_cloud_created": "Lær Gimi at kende!",
  "event_add_email_change_number": "Tilføj din e-mail! Det er godt at have, hvis du skulle skifte dit nummer...",
  "push_receive_first_money": "Du har modtaget dine første penge!",
  "event_got_weekly_allowance": "Du har nu ugentlige lommepenge",
  "event_got_monthly_allowance": "Du har nu månedlige lommepenge",
  "event_got_a_new_chore": "{parent.nickname} har sendt dig en ny opgave",
  "push_got_a_new_chore": "Du har en ny opgave fra {parent.nickname}",
  "push_got_x_new_chores": "Du har nye opgaver! Du kan tjene flere penge!",
  "push_chore_was_not_approved": "{chore.title} er ikke blevet godkendt af {parent.nickname}",
  "push_chore_was_approved": "{chore.title} er blevet godkedt af {parent.nickname}",
  "event_you_have_reached_a_dream_parent": "{goal.child.nickname} har nået en drøm",
  "event_you_have_reached_a_dream_child": "Du har nået en drøm",
  "event_reached_a_dream": "Du har opnået din drøm",
  "push_the_new_weekly_tasks": "Ny uge, nye opgaver, flere penge at tjene! 💰",
  "push_reminder_of_chore": "{parent.nickname} minder dig om at lave opgaven {chore.title}",
  "event_create_a_new_dream": "{parent.nickname} har lavet en hævning fra din Sky.",
  "push_withdrawal_made_from_your_cloud": "{parent.nickname} har lavet en fratrækning fra din opsparing.",
  "push_deposit_made_to_your_cloud": "Penge er blevet tilføjet din opsparing!",
  "push_suggested_chore_enabled": "Du har en ny opgave, der venter på at blive lavet!",
  "event_upgraded_to_premium": "Du er blevet opgraderet til premium",
  "push_upgraded_to_premium": "Gimi kortet er på vej! Gå til appen for mere info!",
  "event_not_paid_card_locked": "Du har ikke betalt abonnementet for {child.nickname}, kontoen er låst indtil du betaler. ",
  "event_influence_use_gimi": "Se hvordan influencere bruger Gimi! ",
  "event_allowance_is_set_for_you_weekly": "{parent.nickname} giver dig nu lommepenge",
  "event_allowance_is_set_for_you_monthly": "{parent.nickname} giver dig nu lommepenge",
  "event_suggestion_of_new_allowance_weekly": "Foreslag til nye lommepenge",
  "event_suggestion_of_new_allowance_monthly": "Foreslag til nye lommepenge",
  "event_allowance_settings_are_updated_weekly": "Lommepengeindstillinger er blevet opdateret",
  "event_allowance_settings_are_updated_monthly": "Lommepengeindstillinger er blevet opdateret",
  "event_you_have_set_allowance_weekly": "Du har indstillet lommepenge",
  "event_you_have_set_allowance_monthly": "Du har indstillet lommepenge",
  "event_allowance_is_set_for_you": "{parent.nickname} giver dig nu lommepenge",
  "event_suggestion_of_new_allowance": "Foreslag til nye lommepenge",
  "event_allowance_settings_are_updated": "Lommepengeindstillinger er blevet opdateret",
  "event_you_have_set_allowance": "Du har sat lommepenge",
  "event_got_x_new_chores": "{parent.nickname} har sendt dig en række nye opgaver",
  "event_ready_for_apple_pay": "Dit Gimi kort er klar til Apple Pay! Du kan bruge det, når du ser det kontaktløse ikon",
  "push_ready_for_apple_pay": "Dit Gimi kort er klar til Apple Pay! ",
  "event_wait_active_for_apple_pay": "Dit Gimi kort venter på at blive aktiveret til Apple Pay!",
  "push_wait_active_for_apple_pay": "Dit Gimi kort er klar til Apple Pay! ",
  "event_spend_more_money_than_have": "Du har brugt flere penge, end hvad du havde på dit kort. Du skal tanke kortet op. ",
  "push_spend_more_money_than_have": "Ups... du har brugt for mange penge ☹️",
  "event_child_spend_more_money": "{child.nickname} har brugt flere penge end hvad der var på kortet. Kontakt us, hvis du har brug for hjælp!",
  "event_payday_transfer_money": "Det er payday for {child.nickname}! ",
  "push_payday_transfer_money": "Det er payday for {child.nickname}! 💫 Overfør penge nu",
  "event_premium_payday_parent": "Det er payday! 💫 Overfør penge til dine børn",
  "push_promo_week_51_child": "Giv nogen et kompliment i dag! 🤘- Piggy",
  "push_promo_week_52_child": "Hav en skøn dag 🌈 - Piggy",
  "push_promo_week_1_child": "Penge kan ikke købe dig glæde 😇",
  "push_promo_week_2_child": "Du er fantastisk 🌼 - Piggy",
  "push_promo_week_3_child": "Nyd din dag 🥰 - Piggy",
  "push_promo_week_4_child": "Hvad laver du i dag? - Piggy",
  "push_promo_week_5_child": "Hej, hvad så? - Piggy",
  "push_promo_week_6_child": "Lav nogle opgaver i dag! - Piggy",
  "push_promo_week_7_child": "Giv noget kærlighed i dag 🌼 - Piggy",
  "push_promo_week_8_child": "Vil du tjekke din opsparing ud? - Piggy",
  "push_promo_week_9_child": "Du er sej! 😜 - Piggy",
  "push_promo_week_10_child": "Har du lyst til at snakke? - Piggy",
  "push_promo_week_11_child": "God lørdag! 🥳 - Piggy",
  "push_promo_week_12_child": "Har du brug for det, eller vil du bare have det? ",
  "push_promo_week_13_child": "Pas godt på din opsparing! - Piggy",
  "push_promo_week_51_parent": "Hav en god dag! 🌈",
  "push_promo_week_52_parent": "Tid til at tjekke næste uges opgaver ud?",
  "push_promo_week_1_parent": "Dine børn lærer om penge!",
  "push_promo_week_3_parent": "Har du købt noget til dine børn for nyligt? ✨",
  "push_promo_week_4_parent": "Lørdage er de bedste dage ☀️",
  "push_promo_week_5_parent": "I dag bliver en god dag 💕",
  "push_promo_week_6_parent": "Hvor meget sparer dine børn op?",
  "push_promo_week_7_parent": "God lørdag! 🥳",
  "push_promo_week_8_parent": "Bruger dine børn for mange penge?",
  "push_promo_week_9_parent": "Hvordan er dine børns pengefærdigheder?",
  "push_promo_week_10_parent": "Husk at trække penge fra for slik!",
  "push_promo_week_11_parent": "Lad os snakke om penge i dag!",
  "push_promo_week_12_parent": "Er der flere udgifter fra dine børn det seneste stykke tid?",
  "push_promo_week_13_parent": "Hvad er dit bedste opsparingsråd?",
  "push_promo_week_14_parent": "Lad børnene lave nogle opgaver i dag!",
  "push_promo_week_15_parent": "Nyd din dag 🥰",
  "push_promo_week_16_parent": "Giv din familie noget kærlighed i dag",
  "connect_sms_template_parent": "Hej! {connection_token.created_by.nickname} venter på dig i Gimi appen. Klik her for at starte med at håndtere penge sammen  {connection_token.accept_url}",
  "connect_sms_template_child": "Hej! {connection_token.created_by.nickname} venter på dig i Gimi appen. Klik her for at starte med at håndtere penge sammen! {connection_token.accept_url}",
  "ADGEON019_notification_title": "Du er på Gimi Kort ventelisten!",
  "event_short_tutorial": "Hvordan man bruger Gimi på 20 sekunder",
  "ADGEPU006_notification_title": "Problemer med at få logget dit barn ind? Du kan nu tilføje et telefonnummer i dit barns indstillinger, så de kan logge ind igen!",
  "push_child_spend": "💳 Du har lige brugt {pfstransactionstatement.str_amount} hos {pfstransactionstatement.merchant_name}",
  "push_child_spend_to_parent": "💳 {child.nickname} har lige brugt {pfstransactionstatement.str_amount} hos {pfstransactionstatement.merchant_name}",
  "push_purchases_with_card": "💳 Du har lige brugt {pfstransactionstatement.str_amount} hos {statement.merchant_name}",
  "CHGERE030_push_title": "Du har en ny opgave, der venter på at blive lavet!",
  "CHGERE030_notification_title": "{parent.nickname} har accepteret dit opgave forslag!",
  "push_add_chores": "{child.nickname} har ingen opgaver endnu. Vi har nogle opgave forslag!",
  "CHGERE031_notification_title": "Du har ingen opgaver i dag!",
  "event_add_deposit_to_savings": "Tid til at booste opsparingen for {child.nickname}? Klik her for at tilføje et beløb!",
  "event_send_invite_reminder": "Din invitation er ikke blevet accepteret. Send en reminder!",
  "ADPRON016_notification_title": "Du er på venteliste til et Gimi kort, og vi er endelig i gang med at tage imod ordrer igen!",
  "ADPRON016_push_title": "Det er din tur næste gang til at få et Gimi kort! Få dit kort nu!",
  "ADGEON017_notification_title": "Bliv forbundet med et barn!",
  "event_chore_was_approved": "{user.nickname} godkendt {task.title}",
  "push_child_has_completed_a_chore": "{assignment.child.nickname} har færdiggjort {assignment.task.title}!",
  "event_child_has_completed_a_chore": "{child.nickname} har færdiggjort {task.title}",
  "push_pfs_payday": "Det er payday! 💫 Overfør penge til dine børn",
  "ADGERE037_notification_title": "{child.nickname} disconnected from you",
  "push_child_disconnected_you": "{child.nickname} har afbrudt sin forbindelse til dig",
  "ADGEPU010_push_title": "Vi har gode nyheder til dig!",
  "ADPRRE029_notification_title": "PLZ_TRANSLATE Reminder from {child.nickname} to deposit money!",
  "ADPRRE029_push_title": "PLZ_TRANSLATE Reminder from {child.nickname} to deposit money!",
  "ADPRRE008_push_title": "PLZ_TRANSLATE {parent.nickname} is requesting permission to deposit to {child.nickname}",
  "ALGEON001_notification_title": "PLZ_TRANSLATE Watch this short movie about Gimi!",
  "CHGEON024_notification_title": "PLZ_TRANSLATE Verify your email address!",
  "CHGEON025_notification_title": "PLZ_TRANSLATE Add your phone number!",
  "CHGERE031_push_title": "PLZ_TRANSLATE You have a chore to do today!",
  "ADPRRE027_push_title": "PLZ_TRANSLATE {child.nickname} spent more money than was on the card...",
  "ADPRRE011_push_title": "PLZ_TRANSLATE Reminder to pay premium subscription",
  "ADPRPU004_push_title": "PLZ_TRANSLATE You have not paid the premium subscription",
  "CHGEON005_push_title": "PLZ_TRANSLATE Your Gimi account has been deleted. Welcome back anytime!",
  "ADGERE015_notification_title": "PLZ_TRANSLATE {child.nickname} has a new connection",
  "CHGERE017_notification_title": "PLZ_TRANSLATE Your invitation was rejected. Invite someone else?",
  "ADGERE016_notification_title": "PLZ_TRANSLATE Your invitation was rejected. Invite someone else?",
  "ADGEON005_push_title": "PLZ_TRANSLATE Add a profile picture!",
  "CHFRRE001_notification_title": "PLZ_TRANSLATE Today is Payday! 🤩",
  "ADGERE011_notification_title": "PLZ_TRANSLATE {child.nickname} has reached a dream",
  "CHGERE033_push_title": "PLZ_TRANSLATE Don't forget you have {savings_balance} in savings! ✌️",
  "CHGERE028_push_title": "PLZ_TRANSLATE You and {ConnectionToken.used_by.nickname} are connected!",
  "CHGERE028_notification_title": "PLZ_TRANSLATE You are now connected with {ConnectionToken.used_by.nickname}!",
  "ADGERE021_notification_title": "PLZ_TRANSLATE You are now connected with {child.nickname}!",
  "ADGERE021_push_title": "PLZ_TRANSLATE You and {child.nickname} are connected!",
  "ADGEON005_notification_title": "PLZ_TRANSLATE Add a profile pic!",
  "event_settle_your_debt": "Afvikl din gæld til {child.nickname}",
  "CHGEON007_notification_title": "PLZ_TRANSLATE Add your picture",
  "ADPRON012_notification_title": "PLZ_TRANSLATE Setup an app passcode"
}